opal_common/__init__.py
opal_common/async_utils.py
opal_common/config.py
opal_common/corn_utils.py
opal_common/emport.py
opal_common/http_utils.py
opal_common/logger.py
opal_common/middleware.py
opal_common/paths.py
opal_common/urls.py
opal_common/utils.py
opal_common/authentication/__init__.py
opal_common/authentication/authz.py
opal_common/authentication/casting.py
opal_common/authentication/deps.py
opal_common/authentication/signer.py
opal_common/authentication/types.py
opal_common/authentication/verifier.py
opal_common/authentication/tests/__init__.py
opal_common/authentication/tests/jwt_signer_test.py
opal_common/cli/__init__.py
opal_common/cli/commands.py
opal_common/cli/docs.py
opal_common/cli/typer_app.py
opal_common/confi/__init__.py
opal_common/confi/cli.py
opal_common/confi/confi.py
opal_common/confi/types.py
opal_common/engine/__init__.py
opal_common/engine/parsing.py
opal_common/engine/paths.py
opal_common/fetcher/__init__.py
opal_common/fetcher/events.py
opal_common/fetcher/fetch_provider.py
opal_common/fetcher/fetcher_register.py
opal_common/fetcher/logger.py
opal_common/fetcher/engine/__init__.py
opal_common/fetcher/engine/base_fetching_engine.py
opal_common/fetcher/engine/core_callbacks.py
opal_common/fetcher/engine/fetch_worker.py
opal_common/fetcher/engine/fetching_engine.py
opal_common/fetcher/providers/__init__.py
opal_common/fetcher/providers/fastapi_rpc_fetch_provider.py
opal_common/fetcher/providers/http_fetch_provider.py
opal_common/fetcher/tests/__init__.py
opal_common/fetcher/tests/failure_handler_test.py
opal_common/fetcher/tests/http_fetch_test.py
opal_common/fetcher/tests/rpc_fetch_test.py
opal_common/git_utils/__init__.py
opal_common/git_utils/branch_tracker.py
opal_common/git_utils/bundle_maker.py
opal_common/git_utils/bundle_utils.py
opal_common/git_utils/commit_viewer.py
opal_common/git_utils/diff_viewer.py
opal_common/git_utils/env.py
opal_common/git_utils/exceptions.py
opal_common/git_utils/repo_cloner.py
opal_common-0.9.3.dist-info/METADATA
opal_common-0.9.3.dist-info/WHEEL
opal_common-0.9.3.dist-info/top_level.txt
opal_common-0.9.3.dist-info/RECORD
