Metadata-Version: 2.1
Name: opal-common
Version: 0.9.3
Summary: OPAL is an administration layer for Open Policy Agent (OPA), detecting changes to both policy and data and pushing live updates to your agents. opal-common contains common code used by both opal-client and opal-server.
Home-page: https://github.com/permitio/opal
Author: Or Weis, Asaf Cohen
Author-email: or@permit.io
License: Apache 2.0
Classifier: Operating System :: OS Independent
Classifier: License :: OSI Approved :: Apache Software License
Classifier: Programming Language :: Python
Classifier: Programming Language :: Python :: 3
Classifier: Programming Language :: Python :: 3.9
Classifier: Programming Language :: Python :: 3.10
Classifier: Programming Language :: Python :: 3.11
Classifier: Programming Language :: Python :: 3.12
Classifier: Topic :: Internet :: WWW/HTTP :: HTTP Servers
Classifier: Topic :: Internet :: WWW/HTTP :: WSGI
Requires-Python: >=3.9
Requires-Dist: aiohttp<4,>=3.9.2
Requires-Dist: click<9,>=8.1.3
Requires-Dist: cryptography
Requires-Dist: gitpython<4,>=3.1.32
Requires-Dist: loguru>=0.6.0
Requires-Dist: pyjwt[crypto]<3,>=2.4.0
Requires-Dist: python-decouple<4,>=3.6
Requires-Dist: tenacity<9,>=8.0.1
Requires-Dist: datadog<1,>=0.44.0
Requires-Dist: ddtrace<4,>=3.0.0
Requires-Dist: certifi>=2023.7.22
Requires-Dist: requests>=2.32.0
Requires-Dist: httpx>=0.27.0
Requires-Dist: urllib3>=2.2.2
Requires-Dist: idna<4,>=3.3
Requires-Dist: typer<1,>=0.4.1
Requires-Dist: fastapi<1,>=0.109.1
Requires-Dist: fastapi-websocket-pubsub[all]<2,>=1.0.0
Requires-Dist: fastapi-websocket-rpc<1,>=0.1.28
Requires-Dist: websockets>=10.3
Requires-Dist: gunicorn>=23.0.0
Requires-Dist: pydantic[email]<2,>=1.9.1
Requires-Dist: starlette<1,>=0.40.0
Requires-Dist: uvicorn[standard]<1,>=0.17.6
Requires-Dist: fastapi-utils<1,>=0.2.1
Requires-Dist: setuptools>=70.0.0
Requires-Dist: anyio>=4.4.0
Requires-Dist: typing-extensions; python_version < "3.8"
